pyroject/__init__.py
pyroject/cli.py
pyroject-0.1.3.dist-info/licenses/LICENSE
pyroject-0.1.3.dist-info/METADATA
pyroject-0.1.3.dist-info/WHEEL
pyroject-0.1.3.dist-info/entry_points.txt
pyroject-0.1.3.dist-info/top_level.txt
pyroject-0.1.3.dist-info/RECORD
